gptcode_cli/__init__.py
gptcode_cli/cli.py
gptcode_cli-0.1.0.dist-info/METADATA
gptcode_cli-0.1.0.dist-info/WHEEL
gptcode_cli-0.1.0.dist-info/entry_points.txt
gptcode_cli-0.1.0.dist-info/RECORD
