Metadata-Version: 2.1
Name: gptcode-cli
Version: 0.1.0
Summary: 
Author: xangcastle
Author-email: xangcastle@gmail.com
Requires-Python: >=3.11,<4.0
Classifier: Programming Language :: Python :: 3
Classifier: Programming Language :: Python :: 3.11
Classifier: Programming Language :: Python :: 3.12
Requires-Dist: click (>=8.1.7,<9.0.0)
Requires-Dist: openai (>=1.7.2,<2.0.0)
Requires-Dist: requests (>=2.31.0,<3.0.0)
